README.rst
setup.py
bunit.egg-info/PKG-INFO
bunit.egg-info/SOURCES.txt
bunit.egg-info/dependency_links.txt
bunit.egg-info/entry_points.txt
bunit.egg-info/not-zip-safe
bunit.egg-info/top_level.txt
unit/__init__.py
unit/errors.py
unit/shell.py
unit/system.py
unit/tools.py