Metadata-Version: 1.1
Name: bunit
Version: 0.1
Summary: Binary unit conversion tool
Home-page: https://github.com/xlucas/bunit
Author: Xavier Lucas
Author-email: xavier_lucas@ymail.com
License: MIT
Platform: UNKNOWN
Classifier: Intended Audience :: System Administrators
Classifier: Development Status :: 3 - Alpha
Classifier: License :: OSI Approved :: GNU General Public License v3 (GPLv3)
Classifier: Programming Language :: Python :: 2
Classifier: Programming Language :: Python :: 2.7
Classifier: Programming Language :: Python :: 3
Classifier: Programming Language :: Python :: 3.5
